podmesh/__init__.py
podmesh/core.py
podmesh/hookspecs.py
podmesh/main.py
podmesh-0.0.1.dist-info/LICENSE
podmesh-0.0.1.dist-info/METADATA
podmesh-0.0.1.dist-info/WHEEL
podmesh-0.0.1.dist-info/top_level.txt
podmesh-0.0.1.dist-info/RECORD
